nameko_grpc/__init__.py
nameko_grpc/channel.py
nameko_grpc/client.py
nameko_grpc/compression.py
nameko_grpc/connection.py
nameko_grpc/constants.py
nameko_grpc/context.py
nameko_grpc/dependency_provider.py
nameko_grpc/entrypoint.py
nameko_grpc/errors.py
nameko_grpc/headers.py
nameko_grpc/inspection.py
nameko_grpc/ssl.py
nameko_grpc/streams.py
nameko_grpc/timeout.py
nameko_grpc-1.5.0.dist-info/LICENSE.txt
nameko_grpc-1.5.0.dist-info/METADATA
nameko_grpc-1.5.0.dist-info/WHEEL
nameko_grpc-1.5.0.dist-info/top_level.txt
nameko_grpc-1.5.0.dist-info/zip-safe
nameko_grpc-1.5.0.dist-info/RECORD
