Metadata-Version: 2.1
Name: nameko-grpc
Version: 1.5.0
Summary: Nameko gRPC extensions
Home-page: http://github.com/nameko/nameko-grpc
Author: Matt Yule-Bennett
License: Apache License, Version 2.0
Platform: UNKNOWN
Classifier: Programming Language :: Python
Classifier: Operating System :: MacOS :: MacOS X
Classifier: Operating System :: POSIX
Classifier: Programming Language :: Python :: 3
Classifier: Programming Language :: Python :: 3.6
Classifier: Programming Language :: Python :: 3.7
Classifier: Programming Language :: Python :: 3.8
Classifier: Programming Language :: Python :: 3.9
Classifier: Topic :: Internet
Classifier: Topic :: Software Development :: Libraries :: Python Modules
Classifier: Intended Audience :: Developers
Requires-Dist: nameko (>=3.0.0-rc9)
Requires-Dist: h2 (>=3)
Requires-Dist: grpcio
Requires-Dist: protobuf
Provides-Extra: dev
Requires-Dist: coverage ; extra == 'dev'
Requires-Dist: pytest ; extra == 'dev'
Requires-Dist: grpcio-tools ; extra == 'dev'
Requires-Dist: grpcio-status ; extra == 'dev'
Requires-Dist: googleapis-common-protos ; extra == 'dev'
Requires-Dist: wrapt ; extra == 'dev'
Requires-Dist: zmq ; extra == 'dev'
